uzbekistan/__init__.py
uzbekistan/admin.py
uzbekistan/apps.py
uzbekistan/dynamic_importer.py
uzbekistan/filters.py
uzbekistan/fixtures/districts.yaml
uzbekistan/fixtures/regions.yaml
uzbekistan/migrations/0001_initial.py
uzbekistan/migrations/__init__.py
uzbekistan/models.py
uzbekistan/serializers.py
uzbekistan/tests/__init__.py
uzbekistan/tests/conftest.py
uzbekistan/tests/settings.py
uzbekistan/tests/test_admin.py
uzbekistan/tests/test_apps.py
uzbekistan/tests/test_dynamic_importer.py
uzbekistan/tests/test_models.py
uzbekistan/tests/test_serializers.py
uzbekistan/tests/test_views.py
uzbekistan/tests/urls.py
uzbekistan/urls.py
uzbekistan/views.py
uzbekistan-2.8.2.dist-info/METADATA
uzbekistan-2.8.2.dist-info/WHEEL
uzbekistan-2.8.2.dist-info/RECORD
