Metadata-Version: 2.4
Name: uzbekistan
Version: 2.8.2
Summary: A comprehensive Django package providing complete database of Uzbekistan's Regions, Districts & Quarters with multi-language support including Latin, Cyrillic, and Russian versions.
Author: jakhongir
Author-email: ganiyevuzb@gmail.com
Requires-Python: >=3.11,<4.0
Classifier: Programming Language :: Python :: 3
Classifier: Programming Language :: Python :: 3.11
Classifier: Programming Language :: Python :: 3.12
Classifier: Programming Language :: Python :: 3.13
Classifier: Programming Language :: Python :: 3.14
Requires-Dist: django (>=5.0,<6.0)
Requires-Dist: setuptools (>=68.2.2,<69.0.0)
Requires-Dist: twine (>=4.0.2,<5.0.0)
Requires-Dist: wheel (>=0.41.3,<0.42.0)
